GDBKokkos/__init__.py
GDBKokkos/printCrsMatrix.py
GDBKokkos/printUnorderedMap.py
GDBKokkos/printView.py
GDBKokkos/utils.py
GDBKokkos-0.2.1.data/data/LICENSE
GDBKokkos-0.2.1.dist-info/LICENSE
GDBKokkos-0.2.1.dist-info/METADATA
GDBKokkos-0.2.1.dist-info/WHEEL
GDBKokkos-0.2.1.dist-info/top_level.txt
GDBKokkos-0.2.1.dist-info/RECORD
